sentry_ldap/backend.py
sentry_ldap-1.2.16.dist-info/LICENSE.txt
sentry_ldap-1.2.16.dist-info/METADATA
sentry_ldap-1.2.16.dist-info/WHEEL
sentry_ldap-1.2.16.dist-info/top_level.txt
sentry_ldap-1.2.16.dist-info/RECORD
